nestipy_beanie/__init__.py
nestipy_beanie/beanie_builder.py
nestipy_beanie/beanie_module.py
nestipy_beanie-0.1.2.dist-info/LICENSE
nestipy_beanie-0.1.2.dist-info/METADATA
nestipy_beanie-0.1.2.dist-info/WHEEL
nestipy_beanie-0.1.2.dist-info/RECORD
