Metadata-Version: 2.1
Name: nestipy-beanie
Version: 0.1.2
Summary: 
Author: tsiresymila
Author-email: tsiresymila@gmail.com
Requires-Python: >=3.11,<4.0
Classifier: Programming Language :: Python :: 3
Classifier: Programming Language :: Python :: 3.11
Classifier: Programming Language :: Python :: 3.12
Requires-Dist: beanie (>=1.26.0,<2.0.0)
